{
  "precision": 1.0,
  "recall": 0.5,
  "f1": 0.66667,
  "numAT": 37,
  "numAT_avg": 18.5,
  "time": 1612500,
  "pendingSchemaProportion": 0.732,
  "start time": "2025-04-23 14:16:12",
  "method": "FICBS",
  "subject": "bugs\\bash\\execute_cmd.c",
  "max_mfs": 2,
  "status": "success",
  "stdout": "{\"precision\": 1.00000, \"recall\": 0.50000, \"f1\": 0.66667, \"numAT\": 37, \"numAT_avg\": 18.50000, \"time\": 1612500, \"pendingSchemaProportion\": 0.73200}\n",
  "stderr": "",
  "timeout limit": "600s",
  "memory limit": "1G"
}