{
  "precision": 1.0,
  "recall": 1.0,
  "f1": 1.0,
  "numAT": 734,
  "numAT_avg": 18.35,
  "time": 2964400,
  "pendingSchemaProportion": 0.75778,
  "start time": "2025-04-23 12:10:33",
  "method": "FIC",
  "subject": "bugs\\linux\\init\\main.c",
  "max_mfs": 5,
  "status": "success",
  "stdout": "{\"precision\": 1.00000, \"recall\": 1.00000, \"f1\": 1.00000, \"numAT\": 734, \"numAT_avg\": 18.35000, \"time\": 2964400, \"pendingSchemaProportion\": 0.75778}\n",
  "stderr": "",
  "timeout limit": "600s",
  "memory limit": "1G"
}